requezts/__init__.py
requezts/_adapters.py
requezts/_connection.py
requezts/_connectionpool.py
requezts/_poolmanager.py
requezts/_socket.py
requezts/session.py
requezts-0.0.3.dist-info/LICENSE
requezts-0.0.3.dist-info/METADATA
requezts-0.0.3.dist-info/WHEEL
requezts-0.0.3.dist-info/top_level.txt
requezts-0.0.3.dist-info/RECORD
