Metadata-Version: 2.1
Name: requezts
Version: 0.0.3
Summary: HTTP client over encrypted P2P sockets using ZeroTier
Home-page: https://gitlab.com/bostonwalker/requezts
Author: Boston Walker
Author-email: boston@bostonwalker.ca
License: UNKNOWN
Project-URL: Documentation, https://requezts.readthedocs.io/en/latest/
Project-URL: Tracker, https://gitlab.com/bostonwalker/requezts/-/issues
Platform: UNKNOWN
Classifier: Development Status :: 3 - Alpha
Classifier: Programming Language :: Python :: 3.7
Classifier: License :: OSI Approved :: Apache Software License
Classifier: Operating System :: OS Independent
Classifier: Topic :: Internet :: WWW/HTTP :: Session
Requires-Python: >=3.7
License-File: LICENSE
Requires-Dist: libzt (>=1.4.2)
Requires-Dist: requests (>=2.26.0)
Requires-Dist: urllib3 (>=1.26.7)
Provides-Extra: test
Requires-Dist: pytest ; extra == 'test'
Requires-Dist: starlette ; extra == 'test'
